MANIFEST.in
README.txt
setup.cfg
setup.py
Products/__init__.py
Products.BastionCrypto.egg-info/PKG-INFO
Products.BastionCrypto.egg-info/SOURCES.txt
Products.BastionCrypto.egg-info/dependency_links.txt
Products.BastionCrypto.egg-info/entry_points.txt
Products.BastionCrypto.egg-info/namespace_packages.txt
Products.BastionCrypto.egg-info/not-zip-safe
Products.BastionCrypto.egg-info/requires.txt
Products.BastionCrypto.egg-info/top_level.txt
Products/BastionCrypto/BastionCertAuthority.py
Products/BastionCrypto/BastionPGPKey.py
Products/BastionCrypto/BastionPGPKeyGenerator.py
Products/BastionCrypto/BastionPGPKeyLDAPRepository.py
Products/BastionCrypto/BastionPGPKeyRecord.py
Products/BastionCrypto/BastionPGPKeyRepBase.py
Products/BastionCrypto/BastionPGPKeyZopeRepository.py
Products/BastionCrypto/BastionX509Generator.py
Products/BastionCrypto/CREDITS
Products/BastionCrypto/ChangeLog
Products/BastionCrypto/LICENCE.txt
Products/BastionCrypto/MANIFEST
Products/BastionCrypto/Permissions.py
Products/BastionCrypto/README.txt
Products/BastionCrypto/SignedDocument.py
Products/BastionCrypto/__init__.py
Products/BastionCrypto/bastioncrypto
Products/BastionCrypto/config.py
Products/BastionCrypto/configure.zcml
Products/BastionCrypto/gpg.exp
Products/BastionCrypto/refresh.txt
Products/BastionCrypto/version.txt
Products/BastionCrypto/x509.exp
Products/BastionCrypto/x509.sh
Products/BastionCrypto/Extensions/Install.py
Products/BastionCrypto/Extensions/__init__.py
Products/BastionCrypto/help/add.stx
Products/BastionCrypto/help/edit.stx
Products/BastionCrypto/help/generate.stx
Products/BastionCrypto/help/search.stx
Products/BastionCrypto/man/bastioncrypto.1
Products/BastionCrypto/profiles/default/factorytool.xml
Products/BastionCrypto/profiles/default/metadata.xml
Products/BastionCrypto/profiles/default/skins.xml
Products/BastionCrypto/profiles/default/types.xml
Products/BastionCrypto/profiles/default/types/BastionCertAuthority.xml
Products/BastionCrypto/profiles/default/types/BastionPGPKeyZopeRepository.xml
Products/BastionCrypto/profiles/default/types/BastionX509Generator.xml
Products/BastionCrypto/profiles/default/types/SignedDocument.xml
Products/BastionCrypto/schema/openPGPKey.schema
Products/BastionCrypto/schema/pgp-keyserver.schema
Products/BastionCrypto/schema/setup.ldif
Products/BastionCrypto/schema/slapd.conf
