Metadata-Version: 1.0
Name: Products.BastionCrypto
Version: 4.0.2
Summary: Zope/Plone PKI Suite
Home-page: http://www.last-bastion.net/forge/BastionCrypto
Author: Alan Milligan
Author-email: alan.milligan@last-bastion.net
License: GPL
Keywords: BastionCrypto
Platform: UNKNOWN
Classifier: Framework :: Plone
Classifier: Programming Language :: Python
Classifier: Development Status :: 5 - Production/Stable
Classifier: License :: OSI Approved :: GNU General Public License (GPL)
Classifier: Topic :: Security :: Cryptography
